slithyt/__init__.py
slithyt/build.py
slithyt/cli.py
slithyt/generator.py
slithyt/pronounce.py
slithyt/rhyme.py
slithyt/sentiment.py
slithyt/utils.py
slithyt/validator.py
slithyt/data/__init__.py
slithyt-1.0.0.dist-info/licenses/LICENSE
slithyt-1.0.0.dist-info/METADATA
slithyt-1.0.0.dist-info/WHEEL
slithyt-1.0.0.dist-info/entry_points.txt
slithyt-1.0.0.dist-info/top_level.txt
slithyt-1.0.0.dist-info/RECORD
