Metadata-Version: 2.4
Name: slithyt
Version: 1.0.0
Summary: A tool for generating novel, pronounceable words based on linguistic corpuses.
Author-email: Daniel Hardman <daniel.hardman@gmail.com>
License: MIT License
Project-URL: Homepage, https://github.com/dhh1128/slithyt
Project-URL: Bug Tracker, https://github.com/dhh1128/slithyt/issues
Keywords: word generation,procedural generation,nlp,linguistics,naming
Classifier: Programming Language :: Python :: 3
Classifier: License :: OSI Approved :: MIT License
Classifier: Operating System :: OS Independent
Classifier: Topic :: Text Processing :: Linguistic
Classifier: Development Status :: 4 - Beta
Requires-Python: >=3.8
License-File: LICENSE
Requires-Dist: pronouncing
Requires-Dist: vaderSentiment
Dynamic: license-file
